undetected_chrome_mcp/__init__.py
undetected_chrome_mcp/chrome_manager.py
undetected_chrome_mcp/server.py
undetected_chrome_mcp/server_backup.py
undetected_chrome_mcp/server_complete.py
undetected_chrome_mcp/server_debug.py
undetected_chrome_mcp/server_fixed.py
undetected_chrome_mcp/server_minimal.py
undetected_chrome_mcp/server_proper.py
undetected_chrome_mcp/server_single.py
undetected_chrome_mcp/anti_detection/__init__.py
undetected_chrome_mcp/handlers/__init__.py
undetected_chrome_mcp/handlers/interaction_handler.py
undetected_chrome_mcp/handlers/javascript_handler.py
undetected_chrome_mcp/handlers/navigation_handler.py
undetected_chrome_mcp/handlers/navigation_wrapper.py
undetected_chrome_mcp/handlers/screenshot_handler.py
undetected_chrome_mcp/handlers/tool_wrappers.py
undetected_chrome_mcp/tools/__init__.py
undetected_chrome_mcp/tools/debug_tools.py
undetected_chrome_mcp/tools/interaction_tools.py
undetected_chrome_mcp/tools/javascript_tools.py
undetected_chrome_mcp/tools/navigation_tools.py
undetected_chrome_mcp/tools/screenshot_tools.py
undetected_chrome_mcp_server-1.1.0.dist-info/licenses/LICENSE
undetected_chrome_mcp_server-1.1.0.dist-info/METADATA
undetected_chrome_mcp_server-1.1.0.dist-info/WHEEL
undetected_chrome_mcp_server-1.1.0.dist-info/entry_points.txt
undetected_chrome_mcp_server-1.1.0.dist-info/top_level.txt
undetected_chrome_mcp_server-1.1.0.dist-info/RECORD
