Metadata-Version: 2.4
Name: undetected-chrome-mcp-server
Version: 1.1.0
Summary: Undetected ChromeDriver MCP server with network traffic monitoring for enhanced browser automation with anti-detection capabilities
Author-email: Andrew Lewin <andrewlwn77@users.noreply.github.com>
License: MIT
Project-URL: Homepage, https://github.com/andrewlwn77/undetected-chrome-mcp-server
Project-URL: Repository, https://github.com/andrewlwn77/undetected-chrome-mcp-server
Project-URL: Issues, https://github.com/andrewlwn77/undetected-chrome-mcp-server/issues
Classifier: Development Status :: 4 - Beta
Classifier: Intended Audience :: Developers
Classifier: License :: OSI Approved :: MIT License
Classifier: Programming Language :: Python :: 3
Classifier: Programming Language :: Python :: 3.8
Classifier: Programming Language :: Python :: 3.9
Classifier: Programming Language :: Python :: 3.10
Classifier: Programming Language :: Python :: 3.11
Classifier: Programming Language :: Python :: 3.12
Requires-Python: >=3.8
License-File: LICENSE
Requires-Dist: mcp>=1.0.0
Requires-Dist: undetected-chromedriver>=3.5.0
Requires-Dist: selenium>=4.15.0
Requires-Dist: Pillow>=10.0.0
Requires-Dist: python-dotenv>=1.0.0
Requires-Dist: typing-extensions>=4.0.0
Provides-Extra: dev
Requires-Dist: pytest>=7.0.0; extra == "dev"
Requires-Dist: pytest-asyncio>=0.21.0; extra == "dev"
Requires-Dist: black>=23.0.0; extra == "dev"
Requires-Dist: isort>=5.12.0; extra == "dev"
Requires-Dist: mypy>=1.0.0; extra == "dev"
Requires-Dist: ruff>=0.1.0; extra == "dev"
Dynamic: license-file
